[
    {
        "question": "1.国家秘密是关系国家安全和利益，依照法定程序确定，在一定时间内只限一定范围的人员知悉的事项。",
        "answer": true
    },
    {
        "question": "2.一切国家机关、武装力量、政党、社会团体、企业事业单位和公民都有保守国家秘密的义务。",
        "answer": true
    },
    {
        "question": "3.单位可以把知悉国家秘密作为一种行政级别待遇，按照行政级别确定国家秘密知悉范围。",
        "answer": false
    },
    {
        "question": "4.国家秘密知悉范围内的机关、单位，其有关工作人员不在知悉范围内，但因工作需要知悉国家秘密的，应当经单位负责人批准。",
        "answer": true
    },
    {
        "question": "5.国家秘密知悉范围之外的人员，因工作需要确需知悉国家秘密的，应当经本单位负责人同意。",
        "answer": false
    },
    {
        "question": "6.单位负责人为本单位的定密负责人，对定密工作负总责。",
        "answer": true
    },
    {
        "question": "7.单位对所产生的国家秘密事项，应当按照保密事项范围的规定确定密级，同时确定保密期限和知悉范围。",
        "answer": true
    },
    {
        "question": "8.国家秘密变更后，原定密机关、单位应及时在原国家秘密标志附近重新做出国家秘密标志，并书面通知知悉范围内的机关、单位和人员。",
        "answer": true
    },
    {
        "question": "9.单位对已定密事项是否属于国家秘密或者属于何种密级有不同意见的，不得向原定密机关、单位提出异议。",
        "answer": false
    },
    {
        "question": "10.涉密岗位是指在日常工作中产生、经管或者经常接触、知悉国家秘密事项的岗位。",
        "answer": true
    },
    {
        "question": "11.涉密人员在非涉密出版物上发表文章、著作，不得涉及国家秘密。",
        "answer": true
    },
    {
        "question": "12.涉密人员禁止向境外期刊等新闻出版机构投寄稿件。",
        "answer": false
    },
    {
        "question": "13.涉密人员发表文章、著作凡涉及本单位、本系统业务工作的，应当事先经本单位或上级机关、单位保密审查、审批。",
        "answer": true
    },
    {
        "question": "14.涉密载体是指以文字、数据、符号、图形、图像、声音等方式记载国家秘密信息的纸介质、光介质、电磁介质等各类物品。",
        "answer": true
    },
    {
        "question": "15.制作涉密载体应当在符合保密要求的场所进行。",
        "answer": true
    },
    {
        "question": "16.涉密载体复制件应当加盖复制机关、单位戳记，并视同原件管理。",
        "answer": true
    },
    {
        "question": "17.绝密级涉密载体一般不得复制、摘录、引用、汇编，确有工作需要的，必须征得原定密机关、单位或者其上级机关、单位同意。",
        "answer": true
    },
    {
        "question": "18.涉密载体可以通过普通邮政、快递等渠道传递。",
        "answer": false
    },
    {
        "question": "19.对涉密科研项目文件资料，包括过程文件、电子文档等涉密载体，要进行全面清理、完整归档，个人应根据工作需耍自行妥善保管或者销段。",
        "answer": false
    },
    {
        "question": "20.阅读和使用涉密载体应当在符合保密要求的办公场所进行。",
        "answer": true
    },
    {
        "question": "21.绝密级涉密载体应当在符合国家保密标准的设施、设备中保存，并指定专人管理。",
        "answer": true
    },
    {
        "question": "22.机构撤并时，原机构的涉密载体移交给制发单位时，制发单位不收回的可自行处理。",
        "answer": false
    },
    {
        "question": "23.保密要害部门、部位办公场所在采取必要的保密措施后。仍需要对进入的工勤人员严格监督管理。",
        "answer": true
    },
    {
        "question": "24.专用手机可以随意带入保密要害部门、部位。",
        "answer": false
    },
    {
        "question": "25.未经批准，不得将带有录音、录像、拍照、信息存储功能的设备带入保密要害部门、部位。",
        "answer": true
    },
    {
        "question": "26.涉密会议、活动应当按照“谁承办、谁负责”的原则进行管理。",
        "answer": false
    },
    {
        "question": "27.重要涉密会议、重大涉密活动组织举办者应在必要时，请保密工作机构对保密工作进行监督和指导，并提供必要的安全保密技术服务保障。",
        "answer": true
    },
    {
        "question": "28.保密审查主要是对拟公开发布的信息是否涉及国家秘密进行审查，不需要对是否涉及工作秘密、商业秘密、个人隐私等进行甄别鉴定。",
        "answer": false
    },
    {
        "question": "29.在涉密科研项目结题阶段，要加强成果验收、奖项申报、专利申请等工作的保密管理。",
        "answer": true
    },
    {
        "question": "30.经严格审批，涉及敏感项目(如军工技术、军贸等)的驻外机构和企业可以雇佣外籍人员。",
        "answer": true
    },
    {
        "question": "31.任何组织和个人不得擅自对外提供国家秘密资料。",
        "answer": true
    },
    {
        "question": "32.党的纪律处分条例规定，泄露、扩散或者窃取党组织尚未公开事项或者其他应该保密的内容的，情节较重的，给予开除党籍处分。",
        "answer": false
    },
    {
        "question": "33.“业务工作谁主管，保密工作谁负责”是保密工作的重要原则。",
        "answer": true
    },
    {
        "question": "34.国家秘密的密级分为绝密、机密、秘密三级。",
        "answer": true
    },
    {
        "question": "35.绝密级国家秘密是最重要的国家秘密，泄露会使国家安全和利益遭受特别严重的损害。",
        "answer": true
    },
    {
        "question": "36.机密级国家秘密是重要的国家秘密，泄露会使国家安全和利益遭受严重的损害。",
        "answer": true
    },
    {
        "question": "37.秘密级国家秘密是一般的国家秘密，泄露会使国家安全和利益遭受损害。",
        "answer": true
    },
    {
        "question": "38.保守国家秘密是我国公民的一项基本义务。",
        "answer": true
    },
    {
        "question": "39.涉密岗位根据涉及国家秘密的程度分为核心、重要和一般三个等级。",
        "answer": true
    },
    {
        "question": "40.承担涉密项目研究、建设、管理任务的岗位应确定为重要涉密岗位。",
        "answer": false
    },
    {
        "question": "41.核心涉密岗位是指年产生、处理6件(项)绝密级国家秘密事项的工作岗位。",
        "answer": false
    },
    {
        "question": "42.国防科技工业涉密人员是指取得武器装备科研生产单位保密资格的企业事业单位中，在涉密岗位工作的人员。",
        "answer": true
    },
    {
        "question": "43.涉密人员应当具有中华人民共和国国籍。",
        "answer": true
    },
    {
        "question": "44.涉密人员上岗前要经过保密审查，并接受保密教育培训。",
        "answer": true
    },
    {
        "question": "45.经审查合格，进入涉密岗位的人员须按照规定签订保密承诺书，明确享有的权利和应当承诺履行的保密义务。",
        "answer": true
    },
    {
        "question": "46.单位应当定期对涉密人员进行复审，核心涉密人员每年复审一次，重要涉密人员每2年复审一次，一般涉密人员每3年复审一次。",
        "answer": true
    },
    {
        "question": "47.涉密人员在岗期间，保密工作机构应当会同人事部门，涉密人员所在部门有针对性地对其进行保密教育和检查、考核，对严重违反保密规定的应当及时调离涉密岗位。",
        "answer": true
    },
    {
        "question": "48.一般涉密人员与境外人员通婚或者接受境外机构、组织及非亲属人员资助的，事后向单位报告即可。",
        "answer": false
    },
    {
        "question": "49.涉密人员本人或其直系亲属拟申请获得境外永久居留权、长期居留权或外国国籍的应当向单位报告。",
        "answer": true
    },
    {
        "question": "50.涉密人员离岗后，应当遵守脱密期限规定，核心涉密人员脱密期3年，重要涉密人员脱密期2年，一般涉密人员脱密期1年。",
        "answer": true
    },
    {
        "question": "51.涉密人员脱离涉密岗位3年内不得在境外驻华机构或者外商独资企业工作。",
        "answer": false
    },
    {
        "question": "52.涉密人员脱密期内不得在境外驻华机构或者外商独资企业工作，但可以为境外组织或者人员提供劳务咨询或者其他服务。",
        "answer": false
    },
    {
        "question": "53.涉密人员脱密期内不得在国内中外合资企业工作。",
        "answer": false
    },
    {
        "question": "54.涉密人员因私出境应经所在单位同意，还应按照有关规定办理保密审批手续。",
        "answer": true
    },
    {
        "question": "55.涉密人员因公出国(境)的，应该按照行政隶属关系、干部(人事)管理权限和外事管理权限履行审批程序。",
        "answer": true
    },
    {
        "question": "56.涉密人员脱密期内未经批准可以因私出境。",
        "answer": false
    },
    {
        "question": "57.涉密人员离开涉密岗位后，就不再对本人在原涉密岗位上知悉的国家秘密事项承担保密义务。",
        "answer": false
    },
    {
        "question": "58.涉密人员脱密期满后，对所知悉的国家秘密同样承担保密责任和义务。",
        "answer": true
    },
    {
        "question": "59.出境后可能对国家安全造成危害或者对国家利益造成重大损失的涉密人员，不得批准出境。",
        "answer": true
    },
    {
        "question": "60.涉密人员出国(境)期间受到境外机构、组织和人员的礼品馈赠不须向单位报告。",
        "answer": false
    },
    {
        "question": "61.涉密单位应当对聘用的保安和临时工进行保密教育培训。",
        "answer": true
    },
    {
        "question": "62.在私人交往和通信中不得涉及或泄露国家秘密。",
        "answer": true
    },
    {
        "question": "63.配偶、子女和本人都是涉密人员，互相谈论涉密事项没有关系。",
        "answer": false
    },
    {
        "question": "64.各级国家机关、单位对所产生的国家秘密事项，应当按照国家秘密及其密级具体范围的规定及时确定密级。",
        "answer": true
    },
    {
        "question": "65.定密工作是指对机关、单位业务活动中所产生的国家秘密事项及时、准确确定其密级、保密期限、知悉范围，并对国家秘密载体做出标志，及时通知应当知悉的机关、单位和人员，并按照规定进行全过程管理的活动。",
        "answer": true
    },
    {
        "question": "66.项目定密是指军工单位对从事的武器装备科研生产项目依法进行确定是否涉密以及是何种密级的工作。",
        "answer": true
    },
    {
        "question": "67.国家秘密事项范围定得越宽，密级越高，越有利于国家秘密的安全。",
        "answer": false
    },
    {
        "question": "68.国家秘密的标识为★，★前标密级，★后标保密期限。",
        "answer": true
    },
    {
        "question": "69.纸介质国家秘密载体，其密级和保密期限应在首页(或者封面)标明。",
        "answer": true
    },
    {
        "question": "70.涉及国家秘密的地图、图纸、图表在其标题之后或者下方标明密级和保密期限。",
        "answer": true
    },
    {
        "question": "71.文件、资料汇编中有密件的，应当对各独立密件的密级和保密期限做出国家秘密标志，并在封面或者首页以其中的最低密级和最短保密期限做出国家秘密标志。",
        "answer": false
    },
    {
        "question": "72.摘录、引用密件中属于国家秘密的内容，应当以其中最高密级和最长保密期限做出国家秘密标志。",
        "answer": true
    },
    {
        "question": "73.密件的密级和保密期限变更后，应当在原国家秘密标志位置的附近做出新标志，原标志以明显方式废除。",
        "answer": true
    },
    {
        "question": "74.在保密期限内解密的密件，应当以能够明显识别的方式标明解密的字样。",
        "answer": true
    },
    {
        "question": "75.密品应当在壳体及封面，外包装的显著位置标注国家秘密标志，无法在物品本身标注或者不宜做出国家秘密标志的，应当在密品使用维护说明书中注明密级、保密期限和知悉范围，并提出相应的保密措施。",
        "answer": true
    },
    {
        "question": "76.保密工作机构应当组织相关涉密业务部门研究制定本单位《国家秘密事项范围细目》。",
        "answer": false
    },
    {
        "question": "77.国家秘密事项的密级和保密期限一经确定，就不能改变。",
        "answer": false
    },
    {
        "question": "78.国家秘密的保密期限，除有特殊规定外，绝密级事项不超过20年，机密级事项不超过10年，秘密级事项不超过5年。",
        "answer": false
    },
    {
        "question": "79.保密期限需要缩短的，由原确定密级和保密期限的机关、单位或者上级机关决定。",
        "answer": true
    },
    {
        "question": "80.保密期限需要延长的，由原确定密级和保密期限的机关、单位或者上级机关决定。",
        "answer": true
    },
    {
        "question": "81.单位领导要求继续保密的事项，在领导要求的期限内不得解密。",
        "answer": false
    },
    {
        "question": "82.已解密的事项可以对全社会公开。",
        "answer": false
    },
    {
        "question": "83.企业的技术成果被确定为国家秘密后，在保密期限内不得擅自解密和对外提供。",
        "answer": true
    },
    {
        "question": "84.各级机关和涉密单位编发的内部工作简报都应定为国家秘密。",
        "answer": false
    },
    {
        "question": "85.密级的变更包括降低密级或者提高密级。",
        "answer": true
    },
    {
        "question": "86.制作国家秘密载体应当依照有关规定标明密级和保密期限，注明发放范围及制作数量，并编排序号。",
        "answer": true
    },
    {
        "question": "87.纸介质国家秘密载体应当在本机关、本单位内部文印室或者交保密行政管理部门审查批准的单位制作。",
        "answer": true
    },
    {
        "question": "88.国家秘密载体印制资质单位，使用电子方法排版印制或者打印国家秘密载体的，复制完成后其磁盘内的载体内容可以自行删除。",
        "answer": false
    },
    {
        "question": "89.收发国家秘密载体，应当履行清点、登记、编号、签收等手续。",
        "answer": true
    },
    {
        "question": "90.传递国家秘密载体应当密封包装，装载国家秘密载体的信封或者袋牌上应当标明密级、编号和收发件单位名称。",
        "answer": true
    },
    {
        "question": "91.传递国家秘密载体应当通过机要交通、机要通信或者指派专人传递，不得通过普通邮政渠道传递。",
        "answer": true
    },
    {
        "question": "92.国家秘密文件、资料料可以通过普通邮政“特快专递”传送。",
        "answer": false
    },
    {
        "question": "93.不准通过普通邮政、快递传递属于国家秘密的文件、资料和其他物品。",
        "answer": true
    },
    {
        "question": "94.记录涉密内容应当使用保密本。",
        "answer": true
    },
    {
        "question": "95.单位收到绝密级载体后应当按照规定的范围组织阅读和使用，并对接触和知悉绝密级国家秘密的人员做出文字记载。",
        "answer": true
    },
    {
        "question": "96.单位内部复制国家秘密载体应当履行审批手续，复制机密级以上国家秘密载体须经部门或者单位领导批准，加盖复制戳记，视同原件管理，并进行登记。",
        "answer": true
    },
    {
        "question": "97.因公出差，且两人同行，可以携带密件到购物、餐饮、娱乐等公共场所。",
        "answer": false
    },
    {
        "question": "98.阅读，承办、使用密件，应当在符合保密要求的办公场所进行，严禁擅自携带外出。",
        "answer": true
    },
    {
        "question": "99.传阅秘密公文的人员很多，逐人逐份登记很麻烦，有时可以不登记，收回时自已在文件登记本上画个勾就可以。",
        "answer": false
    },
    {
        "question": "100.某协作单位工作人员因工作需要借阅协作范围内的绝密级图纸，该单位接待人员电话请示有关领导同意后，就可以为其办理借阅手续。",
        "answer": false
    },
    {
        "question": "101.某领导携带涉密U盘参加行业工作会，会议要求报书面材料，因时间紧急，该领导就使用涉密U盘连接营业性场所计算机打印机密级汇报资料，打印完成后作删除处理即可。",
        "answer": false
    },
    {
        "question": "102.某单位进行文件汇编工作时，少量摘抄某涉密文件，经办人员认为该文件汇编册不涉密，可不标注密级。",
        "answer": false
    },
    {
        "question": "103.涉密人员参加会议带回的秘密文件、资料，应交本单位文秘部门或档案部门登记、管理。",
        "answer": true
    },
    {
        "question": "104.阅读和使用国家秘密载体应当办理登记、签收手续。管理人员应当随时掌握国家秘密载体的去向。",
        "answer": true
    },
    {
        "question": "105.传达国家秘密事项时，凡不准记录、录音、录像的，应当事先申明。",
        "answer": true
    },
    {
        "question": "106.不准在普通手机通话中涉及国家秘密。",
        "answer": true
    },
    {
        "question": "107.普通手机处于关机状态下，不存在泄密隐患。",
        "answer": false
    },
    {
        "question": "108.不得使用普通手机短信传送国家秘密信息。",
        "answer": true
    },
    {
        "question": "109.不得使用普通手机中微信、QQ等社交软件谈论、传递国家秘密。",
        "answer": true
    },
    {
        "question": "110.不得将普通手机与涉密信息系统连接。",
        "answer": true
    },
    {
        "question": "111.不得在保密要害部门、部位使用普通手机。",
        "answer": true
    },
    {
        "question": "112.个人因公外出，携带国家秘密载体应当采取严格的保密措施。",
        "answer": true
    },
    {
        "question": "113.因工作需要随身携带密件、密品外出时，不得进入购物、餐饮娱乐等公共场所。",
        "answer": true
    },
    {
        "question": "114.领导干部为了工作方便，可以将密件带回家中处理。",
        "answer": false
    },
    {
        "question": "115.工作人员离开办公场所，应当将国家秘密载体存放在保密设备里。",
        "answer": true
    },
    {
        "question": "116.涉密人员在办公场所阅读、承办、使用密件过程中，需要临时离开，无须将密件存放到保密柜中。",
        "answer": false
    },
    {
        "question": "117.绝密级秘密载体必须放置在安全可靠的密码保险柜中保存，并有专人管理。",
        "answer": true
    },
    {
        "question": "118.销毁国家秘密载体，应当采用物理或者化学的方法彻底销毁，确保信息无法还原。",
        "answer": true
    },
    {
        "question": "119.在不解密的情况下，机密级、秘密级国家秘密技术成果可以申请公开专利或者由保密专利转为公开专利。",
        "answer": false
    },
    {
        "question": "120.公开报道、出版或者个人接受境外媒体采访涉及国家政治、经济、外交、科技、军事方面内容的，不用事先经过审批。",
        "answer": false
    },
    {
        "question": "121.未经批准，严禁公开报道尚属国家秘密的武器装备技术性能指标、科研生产能力、结构布局、产量、发展规划等涉密内容。",
        "answer": true
    },
    {
        "question": "122.机关、单位每年应当定期对当年所存国家秘密载体进行清查、核对，发现问题的应当及时向保密工作机构报告。",
        "answer": true
    },
    {
        "question": "123.销毁纸介质国家秘密载体应当采用焚毁、化浆等方法处理，使用碎纸机销毁的应当使用符合保密要求的碎纸机，送造纸厂销毁的应当送保密行政管理部门指定的造纸厂销毁，并由销毁单位两人以上押运、监销。",
        "answer": true
    },
    {
        "question": "124.U盘上的涉密信息，只要执行删除程序就不可恢复。",
        "answer": false
    },
    {
        "question": "125.国家秘密载体不得作为废品出售。",
        "answer": true
    },
    {
        "question": "126.已拆除硬盘的涉密计算机，可以赠送给希望小学使用。",
        "answer": false
    },
    {
        "question": "127.密品是指直接含有国家秘密信息，或者通过观察、测试、分析等手段能够获取所承载的国家秘密信息的设备和产品。",
        "answer": true
    },
    {
        "question": "128.密品的研制、生产、保存和使用单位应当对密品的密级、保密期限、知悉范围、保密要点的内容进行登记，各环节的交接应当登记签收。",
        "answer": true
    },
    {
        "question": "129.保密要害部门、部位由各机关、单位确定，报国家或者省、自治区、直辖市保密行政管理部门确认或者备案。",
        "answer": true
    },
    {
        "question": "130.保密要害部门、部位应当具备完善可靠的人防、技防、物防措施。",
        "answer": true
    },
    {
        "question": "131.涉密场所使用的进口设备和产品应当进行安全技术检测。",
        "answer": true
    },
    {
        "question": "132.保密要害部门、部位禁止使用无绳电话和普通手机，未经批准不得带入有录音、录像、拍照、信息存储功能的设备。",
        "answer": true
    },
    {
        "question": "133.普通手机关机后可以带入要害部门、部位。",
        "answer": false
    },
    {
        "question": "134.涉密电子文档应当标注国家秘密标志，国家秘密标志不能与正文分离。",
        "answer": true
    },
    {
        "question": "135.不得在涉密计算机和非涉密计算机上交叉使用移动存储介质。",
        "answer": true
    },
    {
        "question": "136.不得使用未采取密码保护的通信系统传输涉密信息。",
        "answer": true
    },
    {
        "question": "137.不得将自己使用的涉密计算机和移动存储介质擅自交给他人使用。",
        "answer": true
    },
    {
        "question": "138.无线电话不保密，军线电话是保密的。",
        "answer": false
    },
    {
        "question": "139.数字移动电话传输的是数字信号，因此是保密的。",
        "answer": false
    },
    {
        "question": "140.在保密通信技术较落后的情况下，允许在单位内部无保密措施的电话中传递国家秘密。",
        "answer": false
    },
    {
        "question": "141.电磁信号泄漏泄密的方式主要是辐射和传导两种方式。",
        "answer": true
    },
    {
        "question": "142.涉密存储介质经文件删除并格式化处理后，仍不得作为非密介质使用。",
        "answer": true
    },
    {
        "question": "143.利用现代通信及计算机网络远程传输国家秘密信息，必须采用密码保护措施，并禁止密明混用。",
        "answer": true
    },
    {
        "question": "144.涉密信息使用的加密措施应当经过国家密码主管部门批准，在任何地方都可以使用。",
        "answer": false
    },
    {
        "question": "145.涉密信息使用的加密措施须经国家密码主管部门批准，并与所保护的信息密级等级相符合。",
        "answer": true
    },
    {
        "question": "146.绝密级信息必须加密存储。",
        "answer": true
    },
    {
        "question": "147.涉密计算机不安装使用无线键盘、无线鼠标、蓝牙、红外设备和无线网卡。",
        "answer": true
    },
    {
        "question": "148.涉密便携式计算机应当拆除具有无线联网功能的硬件模块。",
        "answer": true
    },
    {
        "question": "149.无线联网功能硬件模块无法拆除的计算机禁止作为涉密计算机和信息系统的服务器、用户终端使用。",
        "answer": true
    },
    {
        "question": "150.涉密计算机不得安装来历不明的软件和随意拷贝他人文件。",
        "answer": true
    },
    {
        "question": "151.涉密计算机和移动存储介质应在保密行政管理部门设立的销毁工作机构或者保密行政管理部门指定的单位销毁。",
        "answer": true
    },
    {
        "question": "152.在涉密场所使用的与国际互联网或者其他公共网络连接的计算机不得安装视频、音频等输入装置。",
        "answer": true
    },
    {
        "question": "153.不得在连接国际互联网的计算机上存储和处理涉密信息。",
        "answer": true
    },
    {
        "question": "154 .涉密计算机不得与国际互联网络或者其他公共信息网络相连接。",
        "answer": true
    },
    {
        "question": "155.确因工作需要，可以使用私人计算机处理涉密文件，但要与国际互联网断开连接，待处理完涉密信息后可与互联网连接。",
        "answer": false
    },
    {
        "question": "156.任何单位和个人均不得在国际互联网网络主页、电子公告栏、聊天室、网络新闻组、微博上发布、谈论、张贴、传播国家秘密信息。",
        "answer": true
    },
    {
        "question": "157.为节约开支，可以将淘汰的涉密计算机交本单位非涉密部门使用。",
        "answer": false
    },
    {
        "question": "158.涉密信息系统不得直接或者间接连接国际互联网，必须实行物理隔离。",
        "answer": true
    },
    {
        "question": "159.国家秘密信息不得在与国际互联网连接的计算机和信息系统中存储、处理、传递，但可以在单位内部非涉密单机上存储、处理、传递。",
        "answer": false
    },
    {
        "question": "160.召开涉及国家秘密的会议，使用无线扩音、通信设备不能把音量开得太大。",
        "answer": false
    },
    {
        "question": "161.对参与国家秘密技术研制的科技人员，有关单位不得因其成果不宜公开发表、交流、推广而影响其评奖、表彰和职称的评定。",
        "answer": true
    },
    {
        "question": "162.在对外经济合作中，凡涉及国家秘密的资料未经保密审查和批准，一律不得对外提供。",
        "answer": true
    },
    {
        "question": "163.在对外交往与合作中急需提供国家秘密事项的，可以先提供，后补办手续。",
        "answer": false
    },
    {
        "question": "164.对外交流中除交流内容与谈判口径外，所提供资料和产品应当经过保密审查。",
        "answer": false
    },
    {
        "question": "165.对外公开新闻宣传时，单位代号、真实名称、掩护名称不得同时使用。",
        "answer": true
    },
    {
        "question": "166.接受媒体采访，一般不得涉及国家秘密，特殊情况需要涉及国家秘密的，应当办理审批手续。",
        "answer": true
    },
    {
        "question": "167.音像制品涉及国家秘密的，应按照涉密资料保管。",
        "answer": true
    },
    {
        "question": "168.保密教育和保密提醒是科技交流必须坚持的制度。",
        "answer": true
    },
    {
        "question": "169.对外科技交流活动不得涉及国家秘密，确需涉及国家秘密的应当履行审批手续。",
        "answer": true
    },
    {
        "question": "170.未经批准，任何单位、部门或者个人均不得到保密要害部门、部位进行采访、照相、录像等活动。",
        "answer": true
    },
    {
        "question": "171.使国家秘密被不应知悉者知悉的，属于泄露国家秘密行为。",
        "answer": true
    },
    {
        "question": "172.发现国家秘密载体在使用中下落不明，应当在8小时内向本单位保密工作机构报告，向上级报告不应超过24小时。",
        "answer": true
    },
    {
        "question": "173.国家秘密载体下落不明，自发现之日起，绝密级载体10日内、机密级、秘密载体60日内查无结果的，按照泄密事件处理。",
        "answer": true
    },
    {
        "question": "174.报告泄密事件应当包括被泄露国家秘密的内容、密级、数量及其载体形式、事件发现经过、责任人基本情况、发生的时间、地点及经过。",
        "answer": true
    },
    {
        "question": "175.将涉及国家秘密的计算机和计算机信息系统与国际互联网连接，泄露国家秘密的，应立为泄密案件。",
        "answer": true
    },
    {
        "question": "176.过失泄露一项绝密级国家秘密的可不予立案，在单位内部处理。",
        "answer": false
    },
    {
        "question": "177.违反《中华人民共和国保守国家秘密法》规定，泄露国家秘密，不够刑事处罚的，可以酌情给予行政处分。",
        "answer": true
    },
    {
        "question": "178.以窃取、刺探、收买的方法，非法获取国家秘密的，都应当依据《刑法》追究其刑事责任。",
        "answer": true
    },
    {
        "question": "179.发生泄密事件的机关、单位不及时上报或者隐匿不报的，视情节和造成的后果追究有关人员或者领导人的责任。",
        "answer": true
    },
    {
        "question": "180.未经相应工作部门批准，不得向境外邮寄密品、密件或者随身携带密品、密件出境。",
        "answer": true
    },
    {
        "question": "1.制定《武器装备科研生产单位保密资格认定办法》的目的是进一步规范和加强武器装备科研生产单位保密资格认定工作，确保国家秘密安全。",
        "answer": true
    },
    {
        "question": "2.《武器装备科研生产单位保密资格认定办法》(国保发〔2016〕15号）自2016年6月1日起施行。2008年12月31日印发的《武器装备科研生产单位保密资格审查认证管理办法》(国保发〔2008〕8号)同时废止。",
        "answer": true
    },
    {
        "question": "3.《武器装备科研生产单位保密资格认定办法》适用于承担涉密武器装备科研生产任务的企业事业单位保密资格认定工作。",
        "answer": true
    },
    {
        "question": "4.已承担涉密武器装备科研生产任务的企业事业单位，申请更高级别保密资格，可以免于现场审查。",
        "answer": false
    },
    {
        "question": "5.未取得保密资格的企业事业单位不能承担任何涉密武器装备科研生产任务。",
        "answer": false
    },
    {
        "question": "6.武器装备科研生产一级保密资格单位，可以承担绝密级、机密级、秘密级的科研生产任务。",
        "answer": true
    },
    {
        "question": "7.武器装备科研生产二级保密资格单位，可以承担机密级、秘密级科研生产任务。",
        "answer": true
    },
    {
        "question": "8.武器装备科研生产三级保密资格单位，可以承担机密级、秘密级科研生产任务。",
        "answer": false
    },
    {
        "question": "9.取得保密资格的单位都应当被列入《武器装备科研生产单位保密资格名录》。",
        "answer": true
    },
    {
        "question": "10.申请一、二、三级保密资格的企业事业单位都应当由国家军工保密资格认定委员会进行现场审查。",
        "answer": false
    },
    {
        "question": "11.凡是雇佣外籍人员的单位都不能申请保密资格。",
        "answer": false
    },
    {
        "question": "12.申请保密资格的单位，1年内未发生严重泄密事件，才具备申请保密资格的基本条件。",
        "answer": false
    },
    {
        "question": "13.取得保密资格的单位，资本构成、单位性质发生重大变化的，应当于发生后60个工作日内重新申请。",
        "answer": false
    },
    {
        "question": "14.被注销、暂停、撤销保密资格的单位，自行政决定下发之日起，不得签订新的涉密武器装备科研生产任务合同。",
        "answer": true
    },
    {
        "question": "15.某公司具备申请保密资格的基本条件，但2015年8月18日发生过一起泄密事件，因此，该公司只能到2016年8月18日以后才能申请保密资格。",
        "answer": true
    },
    {
        "question": "16.现场审查结果分为“通过”“不通过”或者“中止”。",
        "answer": true
    },
    {
        "question": "17.现场审查时应当抽取10-30名涉密人员进行保密知识开卷测试。",
        "answer": false
    },
    {
        "question": "18.现场审查时，审查组应当对被审查单位的所有涉密人员进行保密知识测试。",
        "answer": false
    },
    {
        "question": "19.现场审查结束后，审查组应当向被审查单位通报审查意见和结论，对存在的问题提出整改要求。",
        "answer": true
    },
    {
        "question": "20.现场审查时发现被审查单位达不到《评分标准》所列基本项要求的，应当中止审查，并要求其采取整改措施。",
        "answer": true
    },
    {
        "question": "21.现场审查中止的单位，3个月内不重新进行现场审查。",
        "answer": true
    },
    {
        "question": "22.被撤销保密资格的单位，已签订有效合同的，在采取有效保密措施、确保安全保密的情况下可以继续履行合同。",
        "answer": true
    },
    {
        "question": "23.现场审查中止的单位经过3个月整改后，审查组应当恢复审查。",
        "answer": false
    },
    {
        "question": "24.取得保密资格的单位应当实行年度自检制度，每年1月31日前，向作出审批决定的行政机关报送上一年度单位基本情况变化和保密资格标准落实情况自检报告。",
        "answer": true
    },
    {
        "question": "25.对已经取得保密资格满1年的单位，国家和省、自治区、直辖市军工保密资格认定委员会应当进行复查。",
        "answer": false
    },
    {
        "question": "26.省、自治区、直辖市军工保密资格认定委员会对已经取得保密资格单位进行复查时，如果发现被复查单位达不到《评分标准》所列基本项要求的，应当中止复查。",
        "answer": true
    },
    {
        "question": "27.对取得保密资格的单位进行复查时，如果发现被复查单位个别基本项达不到要求，应当视情给予警告、通报、约谈主要负责人，并限期整改。",
        "answer": false
    },
    {
        "question": "28.未通过复查的单位，3个月后重新复查仍未通过的，将撤销其保密资格。",
        "answer": true
    },
    {
        "question": "29.取得保密资格的单位，把涉密武器装备科研生产任务分包给不具有相应保密资格的单位，国家军工保密资格认定委员会将责令其终止分包合同，并限期整改。",
        "answer": false
    },
    {
        "question": "30.已经取得保密资格的单位，选择不具有相应等级保密资格的单位分包涉密武器装备科研生产任务的，除按照规定撤销其保密资格以外，构成犯罪的，要依法追究刑事责任。",
        "answer": true
    },
    {
        "question": "31.取得保密资格的单位，末按照规定进行年度自检的，收回其保密资格证书，撤销其保密资格。",
        "answer": false
    },
    {
        "question": "32.被撤销保密资格的单位，1年内不受理其申请。",
        "answer": true
    },
    {
        "question": "33.取得保密资格的单位，如果擅自引入外商投资的，将撤销其保密资格。",
        "answer": true
    },
    {
        "question": "34.取得保密资格的单位，如果擅自雇佣外籍人员的，应解雇外籍人员，并进行整改",
        "answer": false
    },
    {
        "question": "35.取得保密资格的单位存在重大泄密隐患时，应当撤销该单位的保密资格。",
        "answer": false
    },
    {
        "question": "《武器装备科研生产单位一级保密资格标准》是对申请一级保密资格的单位进行审查认定和复查的依据。",
        "answer": true
    },
    {
        "question": "《武器装备科研生产单位二级保密资格标准》是对申请二级保密资格的单位进行审查认定和复查的依据。",
        "answer": true
    },
    {
        "question": "《武器装备科研生产单位三级保密资格标准》是对申请三级保密资格的单位进行审查认定和复查的依据。",
        "answer": true
    },
    {
        "question": "《武器装备科研生产单位保密资格标准》的实施要求之一是“积极防范，突出重点，严格标准，严格管理”。",
        "answer": false
    },
    {
        "question": "《武器装备科研生产单位保密资格标准》的实施要求之一是“积极防范，突出重点，严格标准，依法管理”。",
        "answer": true
    },
    {
        "question": "《武器装备科研生产单位保密资格标准》的实施要求之一是“业务工作谁主管，保密工作谁负责，促进保密工作与业务工作相融合”。",
        "answer": true
    },
    {
        "question": "保密责任主体是单位法定代表人或者主要负责人，分管保密工作负责人、其他负责人、涉密部门或者项目负责人、涉密人员。",
        "answer": true
    },
    {
        "question": "保密责任主体是分管保密工作负责人和保密工作机构。",
        "answer": false
    },
    {
        "question": "单位其他负责人，应当对分管工作中的保密措施落实情况进行监督检查。",
        "answer": true
    },
    {
        "question": "刘教授是某涉密项目负责人，组织好本项目研究是他的责任，对本项目研究中的保密工作监督检查是单位分管保密工作领导和保密工作机构的责任。",
        "answer": false
    },
    {
        "question": "某单位取得二级保密资格，在承担某涉密科研生产任务过程中发生泄密事件，除追究直接责任人和主管业务负责人的责任外，单位法定代表人也应当承担相应的责任。",
        "answer": true
    },
    {
        "question": "实行保密责任考核追究是落实保密工作责任制的有效措施。",
        "answer": true
    },
    {
        "question": "保密工作机构是指单位保密委员会（保密工作领导小组）。",
        "answer": false
    },
    {
        "question": "保密工作机构是专门负责保密管理工作的职能部门，独立行使保密管理职能。",
        "answer": true
    },
    {
        "question": "申请或者取得保密资格的单位应当成立保密委员会或者保密工作领导小组。",
        "answer": true
    },
    {
        "question": "按照《武器装备科研生产单位保密资格评分标准》规定，保密工作机构设置不符合标准要求的，应当中止审查或者复查。",
        "answer": true
    },
    {
        "question": "单位保密委员会（保密工作领导小组）负责人是通过选举产生或者上级单位指派的。",
        "answer": false
    },
    {
        "question": "申请或者取得三级保密资格的单位可以成立保密委员会。",
        "answer": true
    },
    {
        "question": "一级保密资格单位保密委员会主任由单位负责人担任。",
        "answer": true
    },
    {
        "question": "二级保密资格单位保密委员会主任（保密工作领导小组组长）由单位负责人担任。",
        "answer": true
    },
    {
        "question": "三级保密资格单位保密委员会主任（保密工作领导小组组长）由单位负责人担任。",
        "answer": true
    },
    {
        "question": "一级保密资格单位涉密人员超过100人(含)的，应当确定1名部门负责人担任保密工作机构负责人，配备1名专职保密工作人员。",
        "answer": false
    },
    {
        "question": "一级保密资格单位涉密人员100人(含)以上的，应当设置专门负责保密管理工作的职能部门。",
        "answer": true
    },
    {
        "question": "二级保密资格单位涉密人员200人(含)以上的，应当设置专门负责保密管理工作的职能部门。",
        "answer": true
    },
    {
        "question": "专职保密工作人员是指制作、传递和管理国家秘密载体的人员。",
        "answer": false
    },
    {
        "question": "一级保密资格单位涉密人员1000人(含)以上的，保密工作机构专职工作人员配备不得少于3人。",
        "answer": false
    },
    {
        "question": "二级保密资格单位涉密人员1000人(含)以上的，保密工作机构专职人员配备不得少于4人。",
        "answer": false
    },
    {
        "question": "管理多个法人单位的，其保密工作机构人员配备按照所管理单位涉密人员总数计算。",
        "answer": true
    },
    {
        "question": "某公司申请一级保密资格，涉密人员1205人，已按规定配备4名专职保密工作人员。保密处要求将其中一人调配为保密技术管理人员，但单位主要领导认为保密工作技术含量低，可以不配保密技术管理人员。",
        "answer": false
    },
    {
        "question": "专职保密工作人员2人以上的，应当配备1名保密技术管理人员。",
        "answer": true
    },
    {
        "question": "基本制度是指单位依据国家保密法律法规制定的日常保密管理总的工作规范。",
        "answer": true
    },
    {
        "question": "单位各职能部门应当将保密管理要求融入业务工作制度中，并组织落实。",
        "answer": true
    },
    {
        "question": "重大涉密工程或者项目应当制定专项保密制度。",
        "answer": true
    },
    {
        "question": "某公司具有一级保密资格，已根据工作需要制定保密工作基本制度，公司领导认为内设机构没有必要再制定业务制度和专项制度，这样既便于管理，又节省人力、物力。",
        "answer": false
    },
    {
        "question": "单位保密工作机构对定密工作负主要责任。",
        "answer": false
    },
    {
        "question": "单位主管业务领导、业务部门负有定密工作的主要责任，保密工作机构负有定密工作的组织协调和监督指导的职责。",
        "answer": true
    },
    {
        "question": "界定涉密岗位和涉密人员涉密等级的依据是“以项定岗，以岗定人”，即依据任务或者合同项目原始密级和有关保密范围确定岗位及人员的涉密等级。",
        "answer": true
    },
    {
        "question": "承担机要、档案、密码通信等涉密业务管理的工作人员，不属于专职保密工作人员。",
        "answer": true
    },
    {
        "question": "国家秘密事项在军工科研生产任务期内不需要继续保密的，应当及时解密。",
        "answer": true
    },
    {
        "question": "一个人在涉密工作岗位上干得年限越长，知道的国家秘密就越多，因此，应当根据个人在涉密岗位的工作年限确定涉密等级。",
        "answer": false
    },
    {
        "question": "工作中只要接触绝密级事项的人员，应当被确定为核心涉密人员。",
        "answer": false
    },
    {
        "question": "工作中经常处理、产生、知悉和掌握绝密级事项的人员，应当被确定为核心涉密人员。",
        "answer": true
    },
    {
        "question": "单位聘用涉密人员，不必与其签订保密承诺书，只需在聘用合同上明确保密要求就行。",
        "answer": false
    },
    {
        "question": "单位聘用涉密人员要坚持先审后用的原则，应当进行保密培训并签订保密承诺书。",
        "answer": true
    },
    {
        "question": "对涉密人员的保密管理不只是对涉密人员上岗前的保密审查和培训，还应包括在岗、离岗保密管理。",
        "answer": true
    },
    {
        "question": "单位应当每年对涉密人员进行考核，考核不合格的，应当及时调离涉密岗位。",
        "answer": true
    },
    {
        "question": "涉密人员严重违反保密制度的，应当及时调离涉密岗位。",
        "answer": true
    },
    {
        "question": "取得三级保密资格的单位，每年对涉密人员进行保密教育培训应当每人不少于15学时。",
        "answer": false
    },
    {
        "question": "取得一级保密资格的单位，每年对涉密人员进行保密教育培训应当每人不少于15学时。",
        "answer": true
    },
    {
        "question": "取得二级保密资格的单位，每年对涉密人员进行保密教育培训应当每人不少于15学时。",
        "answer": true
    },
    {
        "question": "取得三级保密资格的单位，每年对涉密人员进行保密教育培训应当每人不少于8学时。",
        "answer": true
    },
    {
        "question": "为确保国家秘密安全，取得保密资格单位的涉密人员不允许因私出国(境)。",
        "answer": false
    },
    {
        "question": "涉密人员因私出国(境)，应当按照规定履行审批手续。",
        "answer": true
    },
    {
        "question": "朱某是某单位的核心涉密人员，2006年8月20日从单位退休，按照国家有关规定，2009年8月20日之前朱某不能到拟聘用他的外资企业做顾问。",
        "answer": true
    },
    {
        "question": "孙某是某单位的一般涉密人员，2007年3月10日从单位辞职后，2008年3月10日之前，他不能到境外机构工作。",
        "answer": true
    },
    {
        "question": "涉密人员脱离单位，都应当与原单位签订保密承诺书。",
        "answer": true
    },
    {
        "question": "凡是国家秘密载体，包括已经定稿或者未定稿的文件和电子文档，都应当按照有关规定标明密级和保密期限。",
        "answer": true
    },
    {
        "question": "制作、收发、传递、使用、复制、保存、维修和销毁国家秘密载体(含纸介质、磁介质和光盘等各类物品)及其过程文件、资料，应当符合国家有关保密管理规定。",
        "answer": true
    },
    {
        "question": "应当根据工作需要，控制国家秘密载体的接触范围。",
        "answer": true
    },
    {
        "question": "绝密级国家秘密载体应当存放在密码文件柜中。",
        "answer": false
    },
    {
        "question": "涉密人员调入其他部门工作，涉密等级和岗位职责发生变化，其使用过的涉密计算机也必须一并带入新部门。",
        "answer": false
    },
    {
        "question": "涉及国家秘密但未定稿的过程文件，可以不按国家秘密载体管理。",
        "answer": false
    },
    {
        "question": "某涉密课题组负责人外出开会需携带一份涉密文件，他找单位保密员借出文件并复印登记后携带外出。",
        "answer": false
    },
    {
        "question": "某涉密人员认为由其使用和管理的移动存储介质中存储大量秘密级信息和一份机密级信息，该介质应当定为秘密级载体。",
        "answer": false
    },
    {
        "question": "密品在研制、生产、试验、运输、保存、维修、使用过程中应当符合国家有关保密管理规定。",
        "answer": true
    },
    {
        "question": "涉密人员辞职、解聘、调离涉密岗位，应当在离岗前清退保管和使用的国家秘密载体。",
        "answer": true
    },
    {
        "question": "一级保密资格单位的保密要害部门应当实行区域隔离，并采取出入口控制、入侵报警、视频监控等技防措施。",
        "answer": true
    },
    {
        "question": "二级保密资格单位的保密要害部门应当采取物理防护，并采取出入口控制、入侵报警、视频监控等技防措施。",
        "answer": false
    },
    {
        "question": "涉及保密要害部门、部位的工程建设项目要符合安全保密要求，所采取的保密防护措施应当经过单位保密工作机构审核，与工程项目同计划、同设计、同建设、同验收。",
        "answer": true
    },
    {
        "question": "携带涉密计算机和移动存储介质外出只要履行审批手续，若带出期间没有使用过，带回后可以不进行保密检查。",
        "answer": false
    },
    {
        "question": "涉密信息系统应当配备系统管理员、安全保密管理员、安全审计员，三员角色可以兼任。",
        "answer": false
    },
    {
        "question": "没有涉密信息系统的单位可以不配备涉密计算机安全保密管理员。",
        "answer": false
    },
    {
        "question": "涉密信息系统与互联网及其他公共信息网络也可以实行逻辑隔离。",
        "answer": false
    },
    {
        "question": "打印机只是输出设备，所以同一台打印机可以根据需要连接在涉密计算机或者非涉密计算机上使用。",
        "answer": false
    },
    {
        "question": "将手机关机后连接到涉密计算机上充电，不会破坏物理隔离。",
        "answer": false
    },
    {
        "question": "存储机密级信息的硬盘经格式化后，可以降密或者解密使用。",
        "answer": false
    },
    {
        "question": "机密级计算机口令长度不得少于6个字符，更换周期不得长于1个月。",
        "answer": false
    },
    {
        "question": "涉密计算机屏幕保护等待时间不得少于10分钟。",
        "answer": false
    },
    {
        "question": "涉密计算机的硬盘发生故障，因为还在保修期内，可以送到厂家进行维修或更换。",
        "answer": false
    },
    {
        "question": "小张的秘密级移动U盘发生故障不能使用，他就使用铁锤将其砸碎，这样处理就符合物理销毁的保密要求。",
        "answer": false
    },
    {
        "question": "涉密计算机因性能不满足使用要求而淘汰，将硬盘和存储部件拆除后，可以捐赠给希望小学使用。",
        "answer": true
    },
    {
        "question": "存储机密级信息的U盘经格式化后，可以降密或者解密使用。",
        "answer": false
    },
    {
        "question": "涉及国家秘密的办公自动化设备可以联入单位非涉密信息系统。",
        "answer": false
    },
    {
        "question": "重要涉密场所禁止使用普通手机和无绳电话。",
        "answer": true
    },
    {
        "question": "禁止使用非涉密办公自动化设备存储和处理涉密信息。",
        "answer": true
    },
    {
        "question": "计算机仅存储一份涉密信息，可以不确定为涉密计算机。",
        "answer": false
    },
    {
        "question": "机密级计算机的身份鉴别如采用用户名加口令的方式，则口令长度应当是十位以上，并以字母、数字和特殊字符混合排列。",
        "answer": true
    },
    {
        "question": "秘密级计算机的身份鉴别如采用用户名加口令的方式，则口令应当每月更换一次。",
        "answer": true
    },
    {
        "question": "涉密计算机如采用USBkey或者IC卡作为身份鉴别工具，拔除USBkey或者IC卡就进入黑屏状态，则可以在操作系统中不设置重鉴别方式(屏幕保护)。",
        "answer": false
    },
    {
        "question": "涉密便携式计算机一般不存储涉密信息，所以涉密便携式计算机丢失不须追究其失密责任。",
        "answer": false
    },
    {
        "question": "带有摄像头的便携式计算机，只要禁止使用摄像功能，就可以作为涉密便携式计算机使用。",
        "answer": false
    },
    {
        "question": "涉密计算机使用的耳机只接收播放的音乐信号，不传递其他信息，所以可以使用无线耳机。",
        "answer": false
    },
    {
        "question": "某单位涉密计算机都是单机管理，一部门为了工作方便自行将部门内几台计算机通过集线器连接，用于共享文件和打印共享。",
        "answer": false
    },
    {
        "question": "为保证自己使用的涉密计算机不受到计算机病毒和恶意代码的攻击，小王经常使用自己的U盘升级计算机病毒和恶意代码样本库。",
        "answer": false
    },
    {
        "question": "将涉密U盘挂在身上，时刻处于自己的监控之中，符合保密要求。",
        "answer": false
    },
    {
        "question": "同一个单位内，涉密等级都相同的人，涉密移动存储介质可以交叉使用。",
        "answer": false
    },
    {
        "question": "机密级以上的涉密计算机，应当采取USB移动存储介质绑定的保护措施。",
        "answer": true
    },
    {
        "question": "携带涉密计算机和存储介质外出期间，为保证安全，应当将涉密计算机和存储介质分由不同的人员管理。",
        "answer": false
    },
    {
        "question": "禁止使用连接国际互联网和其他公共信息网络的信息设备存储和处理涉密信息。",
        "answer": true
    },
    {
        "question": "信息设备只要不连接国际互联网和其他公共信息网络，就可以处理涉密信息。",
        "answer": false
    },
    {
        "question": "为充分利用资源，可以将单台扫描仪连接涉密计算机和非涉密计算机使用。",
        "answer": false
    },
    {
        "question": "应当根据工作需要，配备专供外出携带的涉密计算机和存储介质，并由专人进行集中管理。",
        "answer": true
    },
    {
        "question": "多人使用同一台涉密计算机，每个人对该涉密计算机有相同的使用和管理权限。",
        "answer": false
    },
    {
        "question": "涉密信息设备的报废应当拆除涉密存储部件，将剩余部分作报废处理。",
        "answer": true
    },
    {
        "question": "非涉密信息设备不需要专人管理。",
        "answer": false
    },
    {
        "question": "涉密场所的无绳电话，只要不使用，就不会产生泄密隐患。",
        "answer": false
    },
    {
        "question": "涉密信息设备可以联入单位非涉密的内部办公信息系统。",
        "answer": false
    },
    {
        "question": "信息设备应当粘贴标识，标明密级或者使用用途。",
        "answer": true
    },
    {
        "question": "按照《武器装备科研生产单位保密资格评分标准》规定，涉密信息系统未通过国家保密行政管理部门设立或者授权测评机构的系统测评并存储、处理涉密信息的，中止审查或者复查。",
        "answer": true
    },
    {
        "question": "涉密信息设备或者信息存储设备连接公共信息网络的，中止审查或者复查。",
        "answer": true
    },
    {
        "question": "处理涉密信息的信息设备连接国际互联网或者其他公共信息网络的，中止审查或者复查。",
        "answer": true
    },
    {
        "question": "使用连接国际互联网或者其他公共信息网络的信息设备处理涉密信息的，中止审查或者复查。",
        "answer": true
    },
    {
        "question": "将手机和传真机接入涉密计算机和涉密信息系统，就破坏了物理隔离。",
        "answer": true
    },
    {
        "question": "涉密会议正在进行，麦克风出现问题，服务人员马上取来一支无线麦克风，使会议继续进行。",
        "answer": false
    },
    {
        "question": "由上级单位宣传部门通知的涉及军品科研生产事项的新闻媒体采访，可以不履行审批手续。",
        "answer": false
    },
    {
        "question": "涉密军工单位内部的新闻宣传专栏、刊物登载的新闻宣传材料不需要进行保密审查。",
        "answer": false
    },
    {
        "question": "张某2007年5月从一所二级保密资格高校退休，2007年8月他把自己工作期间从事军品研究的成果写成专著准备出版，张某认为他已退休，其专著属于个人成果，不需要再由单位进行保密审查。",
        "answer": false
    },
    {
        "question": "涉密会议应当在具备安全保密条件的场所召开，重要涉密会议应当在内部场所召开。重要涉密会议主办部门应制定保密方案，落实保密措施，必要时保密工作机构应当派人监督和检查。",
        "answer": true
    },
    {
        "question": "王某参加涉密会议时，为了便于发言和整理相关资料，他带一台具有无线上网功能的便携式计算机进入会场，会议主办方也没有提出异议。",
        "answer": false
    },
    {
        "question": "甲公司为某项涉密武器装备外场试验任务牵头单位，另有3家公司参加。因此，试验现场的保密管理工作由甲公司负责组织协调。",
        "answer": true
    },
    {
        "question": "分包涉密项目，必须选择具有保密资格的单位。",
        "answer": false
    },
    {
        "question": "《武器装备科研生产许可目录》之外的应急或者短期生产的机密级、秘密级涉密项目，选择非保密资格单位的，分包单位应当按照有关保密规定和程序对承制方进行保密审查，签订保密协议，提出保密要求，履行保密监管责任。",
        "answer": false
    },
    {
        "question": "分包涉密项目，没有选择相应保密资格的单位，加重扣分。",
        "answer": false
    },
    {
        "question": "按照《武器装备科研生产单位保密资格评分标准》规定，选择的协作配套单位不具有相应保密资格的，应当中止审查或者复审。",
        "answer": true
    },
    {
        "question": "军工单位在对外交流、合作和谈判等外事活动应当制定保密方案，明确保密事项，采取相应的保密措施，执行保密提醒制度。",
        "answer": true
    },
    {
        "question": "对外交流内容、谈判口径、提供资料和产品应当经过保密审查；涉及国家秘密的，应当按照有关规定履行审批程序。",
        "answer": true
    },
    {
        "question": "涉密部门和涉密人员应当每月进行保密自查，自查及整改情况报单位保密工作机构。",
        "answer": false
    },
    {
        "question": "单位应当每半年组织一次保密检查。",
        "answer": true
    },
    {
        "question": "保密委员会年度内应当组织对单位负责人的保密检查。",
        "answer": true
    },
    {
        "question": "单位发生泄密事件应当按照有关规定及时报告和采取补救措施，并报告查处情况。",
        "answer": true
    },
    {
        "question": "保密工作责任落实情况应当纳入绩效考核，严格执行保密工作责任追究。",
        "answer": true
    },
    {
        "question": "专项保密工作经费用于保密防护设施的建设和设备的配备。",
        "answer": true
    },
    {
        "question": "专项保密工作经费应当列入单位年度财务预算，根据工作需要足额开支。",
        "answer": false
    },
    {
        "question": "保密管理工作经费用于单位日常保密管理工作。",
        "answer": true
    },
    {
        "question": "保密工作档案由保密工作机构和业务部门按照职责分工分别建立。",
        "answer": true
    },
    {
        "question": "保密工作档案保存期限一般不少于2年。",
        "answer": false
    },
    {
        "question": "按照《武器装备科研生产单位保密资格评分标准》的规定，达不到重点项要求的，加重扣分。",
        "answer": true
    },
    {
        "question": "按照《武器装备科研生产单位保密资格评分标准》的规定，达不到重点项要求的，中止审查或者复查。",
        "answer": false
    },
    {
        "question": "按照《武器装备科研生产单位保密资格评分标准》的规定，达不到基本项要求的，应当中止审查或者复查。",
        "answer": true
    }
]